Workbook

Sheet Invoice Template
A1: VENDOR INVOICE
A2: Project 3: Financial Data Architecture & Operational Reporting Dashboard
E3: Tax Rate: | F3: 0.13
B4: Invoice Number: | C4: ="INV-"&TEXT(RANDBETWEEN(1000,9999),"0000") -> INV-6018
B5: Invoice Date: | C5: 2026-06-23
B6: Due Date: | C6: =C5+30 -> 46226
B7: PO Reference: | C7: PO-2026-0042
B9: BILL FROM (Vendor): | E9: BILL TO (Company):
B10: Nexus Supply Co. | E10: Acme Operations Ltd.
B11: 42 Industrial Park Blvd | E11: 100 Corporate Drive, Suite 800
B12: Toronto, ON M5V 2T6 | E12: Toronto, ON M4B 1B3
B13: vendor@nexussupply.com | E13: accounts@acmeops.com
B15: Description | C15: Qty | D15: Unit Price ($) | E15: Amount ($) | F15: Dept Code
B16: Office Supplies — Q2 2026 | C16: 5 | D16: 120 | E16: =C16*D16 -> 600 | F16: CC-001
B17: IT Equipment Lease — June | C17: 1 | D17: 850 | E17: =C17*D17 -> 850 | F17: CC-005
B18: Cleaning Services — Monthly | C18: 4 | D18: 275 | E18: =C18*D18 -> 1100 | F18: CC-001
B19: Marketing Materials — Print Run | C19: 500 | D19: 0.85 | E19: =C19*D19 -> 425 | F19: CC-006
B20: Training Workshop — Finance Team | C20: 8 | D20: 150 | E20: =C20*D20 -> 1200 | F20: CC-002
A25: Subtotal | E25: =SUM(E16:E23) -> 4175
A26: HST / Tax (13%) | E26: =E25*$F$3 -> 542.75
A27: TOTAL DUE ($) | E27: =E25+E26 -> 4717.75
A29: NOTE: Blue text = hardcoded input (user-editable). Black text = formula (locked). Tax rate assumption in cell F3.

Sheet Master Transaction Log
A1: MASTER TRANSACTION LOG — FACT TABLE
A2: Central data source for all pivot tables and the executive dashboard. Do not edit formulas.
A4: Invoice ID | B4: Date | C4: Vendor ID | D4: Vendor Name | E4: Dept Code | F4: Amount ($) | G4: Tax ($) | H4: Total ($) | I4: Payment Status | J4: Days Outstanding
A5: INV-001 | B5: 2026-04-03 | C5: VND-001 | D5: Nexus Supply Co. | E5: CC-001 | F5: 600 | G5: =F5*0.13 -> 78 | H5: =F5+G5 -> 678 | I5: Paid | J5: =IF(I5="Paid",0,TODAY()-DATEVALUE("2026-04-03")) -> 0
A6: INV-002 | B6: 2026-04-10 | C6: VND-002 | D6: TechLease Corp. | E6: CC-005 | F6: 850 | G6: =F6*0.13 -> 110.5 | H6: =F6+G6 -> 960.5 | I6: Paid | J6: =IF(I6="Paid",0,TODAY()-DATEVALUE("2026-04-10")) -> 0
A7: INV-003 | B7: 2026-04-15 | C7: VND-003 | D7: CleanPro Services | E7: CC-001 | F7: 1100 | G7: =F7*0.13 -> 143 | H7: =F7+G7 -> 1243 | I7: Paid | J7: =IF(I7="Paid",0,TODAY()-DATEVALUE("2026-04-15")) -> 0
A8: INV-004 | B8: 2026-04-22 | C8: VND-004 | D8: PrintMasters Inc. | E8: CC-006 | F8: 425 | G8: =F8*0.13 -> 55.25 | H8: =F8+G8 -> 480.25 | I8: Paid | J8: =IF(I8="Paid",0,TODAY()-DATEVALUE("2026-04-22")) -> 0
A9: INV-005 | B9: 2026-05-01 | C9: VND-005 | D9: TrainRight Ltd. | E9: CC-002 | F9: 1200 | G9: =F9*0.13 -> 156 | H9: =F9+G9 -> 1356 | I9: Paid | J9: =IF(I9="Paid",0,TODAY()-DATEVALUE("2026-05-01")) -> 0
A10: INV-006 | B10: 2026-05-05 | C10: VND-001 | D10: Nexus Supply Co. | E10: CC-001 | F10: 740 | G10: =F10*0.13 -> 96.2 | H10: =F10+G10 -> 836.2 | I10: Paid | J10: =IF(I10="Paid",0,TODAY()-DATEVALUE("2026-05-05")) -> 0
A11: INV-007 | B11: 2026-05-12 | C11: VND-002 | D11: TechLease Corp. | E11: CC-005 | F11: 850 | G11: =F11*0.13 -> 110.5 | H11: =F11+G11 -> 960.5 | I11: Pending | J11: =IF(I11="Paid",0,TODAY()-DATEVALUE("2026-05-12")) -> 42
A12: INV-008 | B12: 2026-05-18 | C12: VND-006 | D12: OfficeWorld | E12: CC-003 | F12: 315 | G12: =F12*0.13 -> 40.95 | H12: =F12+G12 -> 355.95 | I12: Pending | J12: =IF(I12="Paid",0,TODAY()-DATEVALUE("2026-05-18")) -> 36
A13: INV-009 | B13: 2026-05-25 | C13: VND-003 | D13: CleanPro Services | E13: CC-001 | F13: 1100 | G13: =F13*0.13 -> 143 | H13: =F13+G13 -> 1243 | I13: Pending | J13: =IF(I13="Paid",0,TODAY()-DATEVALUE("2026-05-25")) -> 29
A14: INV-010 | B14: 2026-06-01 | C14: VND-007 | D14: Meridian Consulting | E14: CC-004 | F14: 4500 | G14: =F14*0.13 -> 585 | H14: =F14+G14 -> 5085 | I14: Pending | J14: =IF(I14="Paid",0,TODAY()-DATEVALUE("2026-06-01")) -> 22
A15: INV-011 | B15: 2026-06-03 | C15: VND-004 | D15: PrintMasters Inc. | E15: CC-006 | F15: 680 | G15: =F15*0.13 -> 88.4 | H15: =F15+G15 -> 768.4 | I15: Overdue | J15: =IF(I15="Paid",0,TODAY()-DATEVALUE("2026-06-03")) -> 20
A16: INV-012 | B16: 2026-06-08 | C16: VND-008 | D16: FacilityPro | E16: CC-001 | F16: 920 | G16: =F16*0.13 -> 119.6 | H16: =F16+G16 -> 1039.6 | I16: Overdue | J16: =IF(I16="Paid",0,TODAY()-DATEVALUE("2026-06-08")) -> 15
A17: INV-013 | B17: 2026-06-10 | C17: VND-005 | D17: TrainRight Ltd. | E17: CC-002 | F17: 960 | G17: =F17*0.13 -> 124.8 | H17: =F17+G17 -> 1084.8 | I17: Disputed | J17: =IF(I17="Paid",0,TODAY()-DATEVALUE("2026-06-10")) -> 13
A18: INV-014 | B18: 2026-06-15 | C18: VND-002 | D18: TechLease Corp. | E18: CC-005 | F18: 850 | G18: =F18*0.13 -> 110.5 | H18: =F18+G18 -> 960.5 | I18: Pending | J18: =IF(I18="Paid",0,TODAY()-DATEVALUE("2026-06-15")) -> 8
A19: INV-015 | B19: 2026-06-20 | C19: VND-009 | D19: Apex Marketing | E19: CC-006 | F19: 2200 | G19: =F19*0.13 -> 286 | H19: =F19+G19 -> 2486 | I19: Pending | J19: =IF(I19="Paid",0,TODAY()-DATEVALUE("2026-06-20")) -> 3
A20: TOTALS | F20: =SUM(F5:F19) -> 17290 | G20: =SUM(G5:G19) -> 2247.7 | H20: =SUM(H5:H19) -> 19537.7

Sheet Vendor Directory
A1: DIMENSION TABLE 1: VENDOR DIRECTORY
A2: Links to Master Transaction Log via Vendor ID
A4: Vendor ID | B4: Vendor Name | C4: Contact Email | D4: Payment Terms | E4: Vendor Tier | F4: Notes
A5: VND-001 | B5: Nexus Supply Co. | C5: billing@nexussupply.com | D5: Net 30 | E5: Tier 1 | F5: Primary office supplies vendor
A6: VND-002 | B6: TechLease Corp. | C6: accounts@techlease.com | D6: Net 45 | E6: Tier 1 | F6: IT equipment leasing
A7: VND-003 | B7: CleanPro Services | C7: invoice@cleanpro.ca | D7: Net 30 | E7: Tier 2 | F7: Monthly cleaning contract
A8: VND-004 | B8: PrintMasters Inc. | C8: billing@printmasters.com | D8: Net 15 | E8: Tier 2 | F8: High volume of disputed invoices
A9: VND-005 | B9: TrainRight Ltd. | C9: accounts@trainright.co | D9: Net 30 | E9: Tier 2 | F9: HR and Finance training
A10: VND-006 | B10: OfficeWorld | C10: ap@officeworld.com | D10: Net 30 | E10: Tier 3 | F10: Occasional furniture and supplies
A11: VND-007 | B11: Meridian Consulting | C11: fees@meridianconsult.com | D11: Net 45 | E11: Tier 1 | F11: Strategic consulting engagements
A12: VND-008 | B12: FacilityPro | C12: billing@facilitypro.ca | D12: Net 30 | E12: Tier 3 | F12: Building maintenance
A13: VND-009 | B13: Apex Marketing | C13: billing@apexmktg.com | D13: Net 30 | E13: Tier 2 | F13: Campaign materials and digital ads

Sheet Department Cost Centers
A1: DIMENSION TABLE 2: DEPARTMENT COST CENTERS
A2: Links to Master Transaction Log via Dept Code
A4: Cost Center Code | B4: Department Name | C4: Dept Head | D4: Annual Budget ($)
A5: CC-001 | B5: Operations | C5: Sarah Mitchell | D5: 120000
A6: CC-002 | B6: Finance | C6: Robert Chen | D6: 85000
A7: CC-003 | B7: Human Resources | C7: Amanda Torres | D7: 60000
A8: CC-004 | B8: Client Services | C8: David Park | D8: 200000
A9: CC-005 | B9: Information Technology | C9: James Okafor | D9: 175000
A10: CC-006 | B10: Marketing | C10: Priya Sharma | D10: 95000

Sheet Executive Dashboard
A1: EXECUTIVE FINANCIAL DASHBOARD — ACCOUNTS PAYABLE OVERVIEW
A2: As of: 2026-06-23 | Source: Master Transaction Log | Currency: CAD ($)
A4: TOTAL INVOICES ($) | E4: TOTAL OVERDUE ($) | I4: INVOICES THIS MONTH
A5: ='Master Transaction Log'!H20 -> 19537.7 | E5: =SUMIF('Master Transaction Log'!I5:I19,"Overdue",'Master Transaction Log'!H5:H19) -> 1808 | I5: =COUNTIFS('Master Transaction Log'!B5:B19,">="&DATE(2026,6,1),'Master Transaction Log'!B5:B19,"<="&DATE(2026,6,30)) -> 0
A8: SPEND BY DEPARTMENT | F8: PAYMENT STATUS BREAKDOWN
A9: Dept Code | B9: Department | C9: Total Invoiced ($) | D9: # Invoices | F9: Status | G9: Count | H9: Total Amount ($) | I9: % of Total
A10: CC-001 | B10: Operations | C10: =SUMIF('Master Transaction Log'!E5:E19,A10,'Master Transaction Log'!H5:H19) -> 5039.8 | D10: =COUNTIF('Master Transaction Log'!E5:E19,A10) -> 5 | F10: Paid | G10: =COUNTIF('Master Transaction Log'!I5:I19,F10) -> 6 | H10: =SUMIF('Master Transaction Log'!I5:I19,F10,'Master Transaction Log'!H5:H19) -> 5553.95 | I10: =IFERROR(H10/SUM($H$10:$H$13),0) -> 0.28426836
A11: CC-002 | B11: Finance | C11: =SUMIF('Master Transaction Log'!E5:E19,A11,'Master Transaction Log'!H5:H19) -> 2440.8 | D11: =COUNTIF('Master Transaction Log'!E5:E19,A11) -> 2 | F11: Pending | G11: =COUNTIF('Master Transaction Log'!I5:I19,F11) -> 6 | H11: =SUMIF('Master Transaction Log'!I5:I19,F11,'Master Transaction Log'!H5:H19) -> 11090.95 | I11: =IFERROR(H11/SUM($H$10:$H$13),0) -> 0.56766917
A12: CC-003 | B12: Human Resources | C12: =SUMIF('Master Transaction Log'!E5:E19,A12,'Master Transaction Log'!H5:H19) -> 355.95 | D12: =COUNTIF('Master Transaction Log'!E5:E19,A12) -> 1 | F12: Overdue | G12: =COUNTIF('Master Transaction Log'!I5:I19,F12) -> 2 | H12: =SUMIF('Master Transaction Log'!I5:I19,F12,'Master Transaction Log'!H5:H19) -> 1808 | I12: =IFERROR(H12/SUM($H$10:$H$13),0) -> 0.09253904
A13: CC-004 | B13: Client Services | C13: =SUMIF('Master Transaction Log'!E5:E19,A13,'Master Transaction Log'!H5:H19) -> 5085 | D13: =COUNTIF('Master Transaction Log'!E5:E19,A13) -> 1 | F13: Disputed | G13: =COUNTIF('Master Transaction Log'!I5:I19,F13) -> 1 | H13: =SUMIF('Master Transaction Log'!I5:I19,F13,'Master Transaction Log'!H5:H19) -> 1084.8 | I13: =IFERROR(H13/SUM($H$10:$H$13),0) -> 0.055523424
A14: CC-005 | B14: IT | C14: =SUMIF('Master Transaction Log'!E5:E19,A14,'Master Transaction Log'!H5:H19) -> 2881.5 | D14: =COUNTIF('Master Transaction Log'!E5:E19,A14) -> 3
A15: CC-006 | B15: Marketing | C15: =SUMIF('Master Transaction Log'!E5:E19,A15,'Master Transaction Log'!H5:H19) -> 3734.65 | D15: =COUNTIF('Master Transaction Log'!E5:E19,A15) -> 3

Sheet Payment Status Reference
A1: DIMENSION TABLE 3: PAYMENT STATUS REFERENCE
A2: Defines valid status codes used in the Master Transaction Log
A4: Status Code | B4: Description | C4: Action Required | D4: Escalate to Manager?
A5: Paid | B5: Invoice received, verified, and payment processed | C5: None — archive invoice | D5: No
A6: Pending | B6: Invoice received, payment not yet initiated | C6: Queue for next payment run | D6: No
A7: Overdue | B7: Payment due date has passed without settlement | C7: Issue payment or escalate immediately | D7: YES
A8: Disputed | B8: Invoice contested due to error, discrepancy, or fraud concern | C8: Hold payment; contact vendor for resolution | D8: YES
