Workbook

Sheet Dashboard
A1: Personal Financial Dashboard
A3: 6-month client financial review, February to July 2026 (sample data)
A5: Total Income (6mo) | C5: Total Expenses (6mo) | E5: Net Savings (6mo) | G5: Avg Savings Rate | I5: Current Net Worth
A6: ='Monthly Summary'!B12 -> 21419.43 | C6: ='Monthly Summary'!C12 -> 15694.31 | E6: ='Monthly Summary'!D12 -> 5725.12 | G6: ='Monthly Summary'!E12 -> 0.26649466 | I6: ='Monthly Summary'!F12 -> 7020

Sheet Read Me
A1: Personal Financial Dashboard
A3: How this workbook works, read this first
A5: Purpose | B5: Tracks income, expenses, budget performance, savings, and net worth over a 6-month period, and rolls it into one dashboard.
A6: Why it matters for advisory work | B6: This is the exact review a banking advisor walks a client through before recommending anything: what is coming in, what is going out, how much budget discipline the client has, and how their net worth is trending. Before an advisor can recommend a TFSA contribution, a debt paydown plan, or a GIC, they need this picture. This workbook is that picture, built as a tool rather than a one-off spreadsheet.
A8: Tabs
A9: 1. Transactions | B9: Every income and expense entry. This is the only sheet you add new rows to.
A10: 2. Budget vs Actual | B10: Monthly budget per category compared to what was actually spent (pulled automatically from Transactions).
A11: 3. Net Worth Tracker | B11: Assets and liabilities by month, and the net worth trend.
A12: 4. Monthly Summary | B12: Income, expenses, savings rate and net worth rolled up by month. Feeds the Dashboard.
A13: 5. Dashboard | B13: One-page view: KPIs, trend charts, expense mix, budget variance.
A15: Colour key
A16: Blue text / yellow fill | B16: Input cells, safe to type over these.
A17: Black text | B17: Formulas. Do not overwrite, they recalculate automatically.
A19: To extend it | B19: Add new rows at the bottom of Transactions with the same columns. The Budget, Net Worth and Summary tabs use SUMIFS ranges that already cover extra rows, so totals update on their own.
A20: Notes | B20: Figures are illustrative (a sample entry-level analyst budget for someone based in Windsor, ON) built to demonstrate structure, formula design and dashboarding. Swap in real numbers and it works the same way.

Sheet Transactions
A1: Transactions
A3: Add new entries at the bottom. Every other tab reads from this sheet
A5: Date | B5: Month | C5: Type | D5: Category | E5: Description | F5: Amount
A6: 46058 | B6: Feb 2026 | C6: Income | D6: Salary | E6: Net pay (biweekly) | F6: 1721.97
A7: 46072 | B7: Feb 2026 | C7: Income | D7: Salary | E7: Net pay (biweekly) | F7: 1691.25
A8: 46070 | B8: Feb 2026 | C8: Income | D8: Freelance | E8: Freelance / tutoring project | F8: 147.91
A9: 46057 | B9: Feb 2026 | C9: Expense | D9: Rent | E9: Monthly apartment rent | F9: 1150
A10: 46071 | B10: Feb 2026 | C10: Expense | D10: Groceries | E10: Grocery run | F10: 306.96
A11: 46067 | B11: Feb 2026 | C11: Expense | D11: Transportation | E11: Transit Windsor monthly pass | F11: 86.11
A12: 46056 | B12: Feb 2026 | C12: Expense | D12: Utilities | E12: Hydro / internet bill | F12: 137.65
A13: 46070 | B13: Feb 2026 | C13: Expense | D13: Phone & Internet | E13: Mobile phone plan | F13: 58.01
A14: 46071 | B14: Feb 2026 | C14: Expense | D14: Subscriptions | E14: Streaming subscriptions | F14: 31.59
A15: 46074 | B15: Feb 2026 | C15: Expense | D15: Dining Out | E15: Dinner / takeout | F15: 151.11
A16: 46067 | B16: Feb 2026 | C16: Expense | D16: Personal Care | E16: Haircut / personal care | F16: 54.92
A17: 46072 | B17: Feb 2026 | C17: Expense | D17: Entertainment | E17: Movies / outings | F17: 70.3
... A87: 46215 | B87: Jul 2026 | C87: Expense | D87: Miscellaneous | E87: Miscellaneous purchase | F87: 127.87

Sheet Budget vs Actual
A1: Budget vs Actual
A3: Monthly Budget is an input (blue). Actuals pull live from Transactions via SUMIFS.
A5: Category | B5: Monthly Budget | C5: Feb Actual | D5: Mar Actual | E5: Apr Actual | F5: May Actual | G5: Jun Actual | H5: Jul Actual | I5: Avg Actual | J5: Variance ($) | K5: Variance (%)
A6: Rent | B6: 1150 | C6: =SUMIFS(Transactions!$F$6:$F$87,Transactions!$D$6:$D$87,$A6,Transactions!$B$6:$B$87,"Feb 2026") -> 1150 | D6: =SUMIFS(Transactions!$F$6:$F$87,Transactions!$D$6:$D$87,$A6,Transactions!$B$6:$B$87,"Mar 2026") -> 1150 | E6: =SUMIFS(Transactions!$F$6:$F$87,Transactions!$D$6:$D$87,$A6,Transactions!$B$6:$B$87,"Apr 2026") -> 1150 | F6: =SUMIFS(Transactions!$F$6:$F$87,Transactions!$D$6:$D$87,$A6,Transactions!$B$6:$B$87,"May 2026") -> 1150 | G6: =SUMIFS(Transactions!$F$6:$F$87,Transactions!$D$6:$D$87,$A6,Transactions!$B$6:$B$87,"Jun 2026") -> 1150 | H6: =SUMIFS(Transactions!$F$6:$F$87,Transactions!$D$6:$D$87,$A6,Transactions!$B$6:$B$87,"Jul 2026") -> 1150 | I6: =AVERAGE(C6:H6) -> 1150 | J6: =I6-B6 -> 0 | K6: =IFERROR(J6/B6,0) -> 0
A7: Groceries | B7: 360 | C7: =SUMIFS(Transactions!$F$6:$F$87,Transactions!$D$6:$D$87,$A7,Transactions!$B$6:$B$87,"Feb 2026") -> 306.96 | D7: =SUMIFS(Transactions!$F$6:$F$87,Transactions!$D$6:$D$87,$A7,Transactions!$B$6:$B$87,"Mar 2026") -> 307.74 | E7: =SUMIFS(Transactions!$F$6:$F$87,Transactions!$D$6:$D$87,$A7,Transactions!$B$6:$B$87,"Apr 2026") -> 313.01 | F7: =SUMIFS(Transactions!$F$6:$F$87,Transactions!$D$6:$D$87,$A7,Transactions!$B$6:$B$87,"May 2026") -> 373.05 | G7: =SUMIFS(Transactions!$F$6:$F$87,Transactions!$D$6:$D$87,$A7,Transactions!$B$6:$B$87,"Jun 2026") -> 354.44 | H7: =SUMIFS(Transactions!$F$6:$F$87,Transactions!$D$6:$D$87,$A7,Transactions!$B$6:$B$87,"Jul 2026") -> 360.96 | I7: =AVERAGE(C7:H7) -> 336.02667 | J7: =I7-B7 -> -23.973333 | K7: =IFERROR(J7/B7,0) -> -0.066592593
A8: Transportation | B8: 110 | C8: =SUMIFS(Transactions!$F$6:$F$87,Transactions!$D$6:$D$87,$A8,Transactions!$B$6:$B$87,"Feb 2026") -> 86.11 | D8: =SUMIFS(Transactions!$F$6:$F$87,Transactions!$D$6:$D$87,$A8,Transactions!$B$6:$B$87,"Mar 2026") -> 106.13 | E8: =SUMIFS(Transactions!$F$6:$F$87,Transactions!$D$6:$D$87,$A8,Transactions!$B$6:$B$87,"Apr 2026") -> 92.33 | F8: =SUMIFS(Transactions!$F$6:$F$87,Transactions!$D$6:$D$87,$A8,Transactions!$B$6:$B$87,"May 2026") -> 115.67 | G8: =SUMIFS(Transactions!$F$6:$F$87,Transactions!$D$6:$D$87,$A8,Transactions!$B$6:$B$87,"Jun 2026") -> 87.22 | H8: =SUMIFS(Transactions!$F$6:$F$87,Transactions!$D$6:$D$87,$A8,Transactions!$B$6:$B$87,"Jul 2026") -> 116.94 | I8: =AVERAGE(C8:H8) -> 100.73333 | J8: =I8-B8 -> -9.2666667 | K8: =IFERROR(J8/B8,0) -> -0.084242424
A9: Utilities | B9: 150 | C9: =SUMIFS(Transactions!$F$6:$F$87,Transactions!$D$6:$D$87,$A9,Transactions!$B$6:$B$87,"Feb 2026") -> 137.65 | D9: =SUMIFS(Transactions!$F$6:$F$87,Transactions!$D$6:$D$87,$A9,Transactions!$B$6:$B$87,"Mar 2026") -> 131.52 | E9: =SUMIFS(Transactions!$F$6:$F$87,Transactions!$D$6:$D$87,$A9,Transactions!$B$6:$B$87,"Apr 2026") -> 154.56 | F9: =SUMIFS(Transactions!$F$6:$F$87,Transactions!$D$6:$D$87,$A9,Transactions!$B$6:$B$87,"May 2026") -> 137.44 | G9: =SUMIFS(Transactions!$F$6:$F$87,Transactions!$D$6:$D$87,$A9,Transactions!$B$6:$B$87,"Jun 2026") -> 150.86 | H9: =SUMIFS(Transactions!$F$6:$F$87,Transactions!$D$6:$D$87,$A9,Transactions!$B$6:$B$87,"Jul 2026") -> 140.45 | I9: =AVERAGE(C9:H9) -> 142.08 | J9: =I9-B9 -> -7.92 | K9: =IFERROR(J9/B9,0) -> -0.0528
A10: Phone & Internet | B10: 60 | C10: =SUMIFS(Transactions!$F$6:$F$87,Transactions!$D$6:$D$87,$A10,Transactions!$B$6:$B$87,"Feb 2026") -> 58.01 | D10: =SUMIFS(Transactions!$F$6:$F$87,Transactions!$D$6:$D$87,$A10,Transactions!$B$6:$B$87,"Mar 2026") -> 57.68 | E10: =SUMIFS(Transactions!$F$6:$F$87,Transactions!$D$6:$D$87,$A10,Transactions!$B$6:$B$87,"Apr 2026") -> 58.24 | F10: =SUMIFS(Transactions!$F$6:$F$87,Transactions!$D$6:$D$87,$A10,Transactions!$B$6:$B$87,"May 2026") -> 56.98 | G10: =SUMIFS(Transactions!$F$6:$F$87,Transactions!$D$6:$D$87,$A10,Transactions!$B$6:$B$87,"Jun 2026") -> 57.65 | H10: =SUMIFS(Transactions!$F$6:$F$87,Transactions!$D$6:$D$87,$A10,Transactions!$B$6:$B$87,"Jul 2026") -> 57.54 | I10: =AVERAGE(C10:H10) -> 57.683333 | J10: =I10-B10 -> -2.3166667 | K10: =IFERROR(J10/B10,0) -> -0.038611111
A11: Subscriptions | B11: 40 | C11: =SUMIFS(Transactions!$F$6:$F$87,Transactions!$D$6:$D$87,$A11,Transactions!$B$6:$B$87,"Feb 2026") -> 31.59 | D11: =SUMIFS(Transactions!$F$6:$F$87,Transactions!$D$6:$D$87,$A11,Transactions!$B$6:$B$87,"Mar 2026") -> 30.63 | E11: =SUMIFS(Transactions!$F$6:$F$87,Transactions!$D$6:$D$87,$A11,Transactions!$B$6:$B$87,"Apr 2026") -> 35.08 | F11: =SUMIFS(Transactions!$F$6:$F$87,Transactions!$D$6:$D$87,$A11,Transactions!$B$6:$B$87,"May 2026") -> 33.67 | G11: =SUMIFS(Transactions!$F$6:$F$87,Transactions!$D$6:$D$87,$A11,Transactions!$B$6:$B$87,"Jun 2026") -> 36.89 | H11: =SUMIFS(Transactions!$F$6:$F$87,Transactions!$D$6:$D$87,$A11,Transactions!$B$6:$B$87,"Jul 2026") -> 31.22 | I11: =AVERAGE(C11:H11) -> 33.18 | J11: =I11-B11 -> -6.82 | K11: =IFERROR(J11/B11,0) -> -0.1705
A12: Dining Out | B12: 150 | C12: =SUMIFS(Transactions!$F$6:$F$87,Transactions!$D$6:$D$87,$A12,Transactions!$B$6:$B$87,"Feb 2026") -> 151.11 | D12: =SUMIFS(Transactions!$F$6:$F$87,Transactions!$D$6:$D$87,$A12,Transactions!$B$6:$B$87,"Mar 2026") -> 161.35 | E12: =SUMIFS(Transactions!$F$6:$F$87,Transactions!$D$6:$D$87,$A12,Transactions!$B$6:$B$87,"Apr 2026") -> 153.33 | F12: =SUMIFS(Transactions!$F$6:$F$87,Transactions!$D$6:$D$87,$A12,Transactions!$B$6:$B$87,"May 2026") -> 106.17 | G12: =SUMIFS(Transactions!$F$6:$F$87,Transactions!$D$6:$D$87,$A12,Transactions!$B$6:$B$87,"Jun 2026") -> 149.42 | H12: =SUMIFS(Transactions!$F$6:$F$87,Transactions!$D$6:$D$87,$A12,Transactions!$B$6:$B$87,"Jul 2026") -> 107.92 | I12: =AVERAGE(C12:H12) -> 138.21667 | J12: =I12-B12 -> -11.783333 | K12: =IFERROR(J12/B12,0) -> -0.078555556
A13: Personal Care | B13: 80 | C13: =SUMIFS(Transactions!$F$6:$F$87,Transactions!$D$6:$D$87,$A13,Transactions!$B$6:$B$87,"Feb 2026") -> 54.92 | D13: =SUMIFS(Transactions!$F$6:$F$87,Transactions!$D$6:$D$87,$A13,Transactions!$B$6:$B$87,"Mar 2026") -> 84.85 | E13: =SUMIFS(Transactions!$F$6:$F$87,Transactions!$D$6:$D$87,$A13,Transactions!$B$6:$B$87,"Apr 2026") -> 65.8 | F13: =SUMIFS(Transactions!$F$6:$F$87,Transactions!$D$6:$D$87,$A13,Transactions!$B$6:$B$87,"May 2026") -> 70.26 | G13: =SUMIFS(Transactions!$F$6:$F$87,Transactions!$D$6:$D$87,$A13,Transactions!$B$6:$B$87,"Jun 2026") -> 75.68 | H13: =SUMIFS(Transactions!$F$6:$F$87,Transactions!$D$6:$D$87,$A13,Transactions!$B$6:$B$87,"Jul 2026") -> 86.51 | I13: =AVERAGE(C13:H13) -> 73.003333 | J13: =I13-B13 -> -6.9966667 | K13: =IFERROR(J13/B13,0) -> -0.087458333
A14: Entertainment | B14: 90 | C14: =SUMIFS(Transactions!$F$6:$F$87,Transactions!$D$6:$D$87,$A14,Transactions!$B$6:$B$87,"Feb 2026") -> 70.3 | D14: =SUMIFS(Transactions!$F$6:$F$87,Transactions!$D$6:$D$87,$A14,Transactions!$B$6:$B$87,"Mar 2026") -> 86.75 | E14: =SUMIFS(Transactions!$F$6:$F$87,Transactions!$D$6:$D$87,$A14,Transactions!$B$6:$B$87,"Apr 2026") -> 109.42 | F14: =SUMIFS(Transactions!$F$6:$F$87,Transactions!$D$6:$D$87,$A14,Transactions!$B$6:$B$87,"May 2026") -> 96.09 | G14: =SUMIFS(Transactions!$F$6:$F$87,Transactions!$D$6:$D$87,$A14,Transactions!$B$6:$B$87,"Jun 2026") -> 96.3 | H14: =SUMIFS(Transactions!$F$6:$F$87,Transactions!$D$6:$D$87,$A14,Transactions!$B$6:$B$87,"Jul 2026") -> 87.94 | I14: =AVERAGE(C14:H14) -> 91.133333 | J14: =I14-B14 -> 1.1333333 | K14: =IFERROR(J14/B14,0) -> 0.012592593
A15: TFSA Transfer | B15: 400 | C15: =SUMIFS(Transactions!$F$6:$F$87,Transactions!$D$6:$D$87,$A15,Transactions!$B$6:$B$87,"Feb 2026") -> 425.88 | D15: =SUMIFS(Transactions!$F$6:$F$87,Transactions!$D$6:$D$87,$A15,Transactions!$B$6:$B$87,"Mar 2026") -> 356.96 | E15: =SUMIFS(Transactions!$F$6:$F$87,Transactions!$D$6:$D$87,$A15,Transactions!$B$6:$B$87,"Apr 2026") -> 418.82 | F15: =SUMIFS(Transactions!$F$6:$F$87,Transactions!$D$6:$D$87,$A15,Transactions!$B$6:$B$87,"May 2026") -> 439.78 | G15: =SUMIFS(Transactions!$F$6:$F$87,Transactions!$D$6:$D$87,$A15,Transactions!$B$6:$B$87,"Jun 2026") -> 414.1 | H15: =SUMIFS(Transactions!$F$6:$F$87,Transactions!$D$6:$D$87,$A15,Transactions!$B$6:$B$87,"Jul 2026") -> 351.95 | I15: =AVERAGE(C15:H15) -> 401.24833 | J15: =I15-B15 -> 1.2483333 | K15: =IFERROR(J15/B15,0) -> 0.0031208333
A16: Miscellaneous | B16: 100 | C16: =SUMIFS(Transactions!$F$6:$F$87,Transactions!$D$6:$D$87,$A16,Transactions!$B$6:$B$87,"Feb 2026") -> 109.81 | D16: =SUMIFS(Transactions!$F$6:$F$87,Transactions!$D$6:$D$87,$A16,Transactions!$B$6:$B$87,"Mar 2026") -> 62.79 | E16: =SUMIFS(Transactions!$F$6:$F$87,Transactions!$D$6:$D$87,$A16,Transactions!$B$6:$B$87,"Apr 2026") -> 108.46 | F16: =SUMIFS(Transactions!$F$6:$F$87,Transactions!$D$6:$D$87,$A16,Transactions!$B$6:$B$87,"May 2026") -> 76.2 | G16: =SUMIFS(Transactions!$F$6:$F$87,Transactions!$D$6:$D$87,$A16,Transactions!$B$6:$B$87,"Jun 2026") -> 69.35 | H16: =SUMIFS(Transactions!$F$6:$F$87,Transactions!$D$6:$D$87,$A16,Transactions!$B$6:$B$87,"Jul 2026") -> 127.87 | I16: =AVERAGE(C16:H16) -> 92.413333 | J16: =I16-B16 -> -7.5866667 | K16: =IFERROR(J16/B16,0) -> -0.075866667
A17: Total | B17: =SUM(B6:B16) -> 2690 | C17: =SUM(C6:C16) -> 2582.34 | D17: =SUM(D6:D16) -> 2536.4 | E17: =SUM(E6:E16) -> 2659.05 | F17: =SUM(F6:F16) -> 2655.31 | G17: =SUM(G6:G16) -> 2641.91 | H17: =SUM(H6:H16) -> 2619.3 | I17: =SUM(I6:I16) -> 2615.7183 | J17: =SUM(J6:J16) -> -74.281667

Sheet Net Worth Tracker
A1: Net Worth Tracker
A3: Account balances are inputs (blue), reconciled at month-end. Net Worth is calculated.
A5: Month | B5: Chequing | C5: Savings | D5: TFSA | E5: Credit Card | F5: Student Loan | G5: Total Assets | H5: Total Liabilities | I5: Net Worth
A6: Feb 2026 | B6: 900 | C6: 3200 | D6: 6100 | E6: 420 | F6: 8200 | G6: =B6+C6+D6 -> 10200 | H6: =E6+F6 -> 8620 | I6: =G6-H6 -> 1580
A7: Mar 2026 | B7: 1050 | C7: 3550 | D7: 6550 | E7: 380 | F7: 8050 | G7: =B7+C7+D7 -> 11150 | H7: =E7+F7 -> 8430 | I7: =G7-H7 -> 2720
A8: Apr 2026 | B8: 980 | C8: 3900 | D8: 7000 | E8: 460 | F8: 7900 | G8: =B8+C8+D8 -> 11880 | H8: =E8+F8 -> 8360 | I8: =G8-H8 -> 3520
A9: May 2026 | B9: 1120 | C9: 4300 | D9: 7480 | E9: 300 | F9: 7750 | G9: =B9+C9+D9 -> 12900 | H9: =E9+F9 -> 8050 | I9: =G9-H9 -> 4850
A10: Jun 2026 | B10: 1000 | C10: 4700 | D10: 7950 | E10: 350 | F10: 7600 | G10: =B10+C10+D10 -> 13650 | H10: =E10+F10 -> 7950 | I10: =G10-H10 -> 5700
A11: Jul 2026 | B11: 1150 | C11: 5150 | D11: 8450 | E11: 280 | F11: 7450 | G11: =B11+C11+D11 -> 14750 | H11: =E11+F11 -> 7730 | I11: =G11-H11 -> 7020

Sheet Monthly Summary
A1: Monthly Summary
A3: Rolls up Transactions and Net Worth Tracker by month. Feeds the Dashboard.
A5: Month | B5: Total Income | C5: Total Expenses | D5: Net Savings | E5: Savings Rate | F5: Net Worth
A6: Feb 2026 | B6: =SUMIFS(Transactions!$F$6:$F$87,Transactions!$C$6:$C$87,"Income",Transactions!$B$6:$B$87,A6) -> 3561.13 | C6: =SUMIFS(Transactions!$F$6:$F$87,Transactions!$C$6:$C$87,"Expense",Transactions!$B$6:$B$87,A6) -> 2582.34 | D6: =B6-C6 -> 978.79 | E6: =IFERROR(D6/B6,0) -> 0.27485377 | F6: ='Net Worth Tracker'!I6 -> 1580
A7: Mar 2026 | B7: =SUMIFS(Transactions!$F$6:$F$87,Transactions!$C$6:$C$87,"Income",Transactions!$B$6:$B$87,A7) -> 3404.78 | C7: =SUMIFS(Transactions!$F$6:$F$87,Transactions!$C$6:$C$87,"Expense",Transactions!$B$6:$B$87,A7) -> 2536.4 | D7: =B7-C7 -> 868.38 | E7: =IFERROR(D7/B7,0) -> 0.25504732 | F7: ='Net Worth Tracker'!I7 -> 2720
A8: Apr 2026 | B8: =SUMIFS(Transactions!$F$6:$F$87,Transactions!$C$6:$C$87,"Income",Transactions!$B$6:$B$87,A8) -> 3594.49 | C8: =SUMIFS(Transactions!$F$6:$F$87,Transactions!$C$6:$C$87,"Expense",Transactions!$B$6:$B$87,A8) -> 2659.05 | D8: =B8-C8 -> 935.44 | E8: =IFERROR(D8/B8,0) -> 0.26024276 | F8: ='Net Worth Tracker'!I8 -> 3520
A9: May 2026 | B9: =SUMIFS(Transactions!$F$6:$F$87,Transactions!$C$6:$C$87,"Income",Transactions!$B$6:$B$87,A9) -> 3741.95 | C9: =SUMIFS(Transactions!$F$6:$F$87,Transactions!$C$6:$C$87,"Expense",Transactions!$B$6:$B$87,A9) -> 2655.31 | D9: =B9-C9 -> 1086.64 | E9: =IFERROR(D9/B9,0) -> 0.29039405 | F9: ='Net Worth Tracker'!I9 -> 4850
A10: Jun 2026 | B10: =SUMIFS(Transactions!$F$6:$F$87,Transactions!$C$6:$C$87,"Income",Transactions!$B$6:$B$87,A10) -> 3729.01 | C10: =SUMIFS(Transactions!$F$6:$F$87,Transactions!$C$6:$C$87,"Expense",Transactions!$B$6:$B$87,A10) -> 2641.91 | D10: =B10-C10 -> 1087.1 | E10: =IFERROR(D10/B10,0) -> 0.2915251 | F10: ='Net Worth Tracker'!I10 -> 5700
A11: Jul 2026 | B11: =SUMIFS(Transactions!$F$6:$F$87,Transactions!$C$6:$C$87,"Income",Transactions!$B$6:$B$87,A11) -> 3388.07 | C11: =SUMIFS(Transactions!$F$6:$F$87,Transactions!$C$6:$C$87,"Expense",Transactions!$B$6:$B$87,A11) -> 2619.3 | D11: =B11-C11 -> 768.77 | E11: =IFERROR(D11/B11,0) -> 0.22690499 | F11: ='Net Worth Tracker'!I11 -> 7020
A12: 6-Month Total / Avg | B12: =SUM(B6:B11) -> 21419.43 | C12: =SUM(C6:C11) -> 15694.31 | D12: =SUM(D6:D11) -> 5725.12 | E12: =AVERAGE(E6:E11) -> 0.26649466 | F12: =F11 -> 7020
